CHANGELOG.md
csv2notion/__init__.py
csv2notion/__main__.py
csv2notion/cli.py
csv2notion/cli_args.py
csv2notion/cli_steps.py
csv2notion/csv_data.py
csv2notion/notion_convert.py
csv2notion/notion_convert_map.py
csv2notion/notion_db.py
csv2notion/notion_db_client.py
csv2notion/notion_db_collection.py
csv2notion/notion_preparator.py
csv2notion/notion_row.py
csv2notion/notion_row_image_block.py
csv2notion/notion_row_upload_file.py
csv2notion/notion_type_guess.py
csv2notion/notion_uploader.py
csv2notion/utils_db.py
csv2notion/utils_exceptions.py
csv2notion/utils_file.py
csv2notion/utils_rand_id.py
csv2notion/utils_static.py
csv2notion/utils_str.py
csv2notion/utils_threading.py
csv2notion/version.py
csv2notion-0.3.9.dist-info/LICENSE
csv2notion-0.3.9.dist-info/METADATA
csv2notion-0.3.9.dist-info/WHEEL
csv2notion-0.3.9.dist-info/entry_points.txt
csv2notion-0.3.9.dist-info/RECORD
