Metadata-Version: 2.1
Name: csv2notion
Version: 0.3.9
Summary: Import/Merge CSV files into Notion database
Home-page: https://github.com/vzhd1701/csv2notion
License: MIT
Keywords: csv,notion,import,merge
Author: vzhd1701
Author-email: vzhd1701@gmail.com
Requires-Python: >=3.7,<4.0
Classifier: Development Status :: 4 - Beta
Classifier: Environment :: Console
Classifier: Intended Audience :: End Users/Desktop
Classifier: License :: OSI Approved :: MIT License
Classifier: Natural Language :: English
Classifier: Operating System :: MacOS
Classifier: Operating System :: Microsoft
Classifier: Operating System :: Unix
Classifier: Programming Language :: Python :: 3
Classifier: Programming Language :: Python :: 3.7
Classifier: Programming Language :: Python :: 3.8
Classifier: Programming Language :: Python :: 3.9
Classifier: Programming Language :: Python :: 3.10
Classifier: Programming Language :: Python :: 3.11
Classifier: Topic :: Internet
Classifier: Topic :: Terminals
Classifier: Topic :: Utilities
Requires-Dist: emoji (>=2.0.0,<3.0.0)
Requires-Dist: notion-vzhd1701-fork (==0.0.37)
Requires-Dist: python-dateutil (>=2.8.2,<3.0.0)
Requires-Dist: requests (>=2.27.1,<2.29)
Requires-Dist: tqdm (>=4.64.0,<5.0.0)
Requires-Dist: types-emoji (>=1.2.8,<2.0.0)
Requires-Dist: types-python-dateutil (>=2.8.16,<3.0.0)
Requires-Dist: types-requests (>=2.27.27,<3.0.0)
Project-URL: Changelog, https://github.com/vzhd1701/csv2notion/blob/master/CHANGELOG.md
Project-URL: Repository, https://github.com/vzhd1701/csv2notion
